<Document>
  # Manipulação de Gás
  Atmos possui uma grande variedade de ferramentas e equipamentos à disposição para a manipulação de gases por toda a estação.

  [bold]Aviso: desancorar (desaparafusar) a maioria dos dispositivos contendo gás vai [color=red]vazar gás[/color] para a atmosfera.[/bold]
  Você pode desancorar com segurança [textlink="cilindros" link="GasCanisters"], [textlink="scubers portáteis" link="PortableScrubber"], [textlink="condensadores" link="GasCondensing"] e [textlink="termomáquinas" link="Thermomachines"].

  <Box>
    <GuideEntityEmbed Entity="GasPipeStraight" Caption=""/>
    <GuideEntityEmbed Entity="GasPipeHalf" Caption=""/>
    <GuideEntityEmbed Entity="GasPipeBend" Caption=""/>
    <GuideEntityEmbed Entity="GasPipeTJunction" Caption=""/>
    <GuideEntityEmbed Entity="GasPipeFourway" Caption=""/>
  </Box>
  <Box>
    ## Tubos
  </Box>
  <Box>
    [color=#999999][italic]Distribuindo gases de um lugar para outro[italic][/color]
  </Box>

  <Box>
    <GuideEntityEmbed Entity="GasPressurePump" Caption=""/>
    <GuideEntityEmbed Entity="GasVolumePump" Caption=""/>
  </Box>
  <Box>
    ## Bombas
  </Box>
  <Box>
    [color=#999999][italic]Forçando o movimento de gases de um lugar para outro[italic][/color]
  </Box>

  <Box>
    <GuideEntityEmbed Entity="GasVentPump" Caption=""/>
    <GuideEntityEmbed Entity="GasPassiveVent" Caption=""/>
    <GuideEntityEmbed Entity="GasOutletInjector" Caption=""/>
    <GuideEntityEmbed Entity="GasVentScrubber" Caption=""/>
    <GuideEntityEmbed Entity="PortableScrubber" Caption=""/>
  </Box>
  <Box>
    ## Entrada e Saída de Atmosfera
  </Box>
  <Box>
    [color=#999999][italic]Inserindo e extraindo gases de uma atmosfera presente (ou não)[/italic][/color]
  </Box>

  <Box>
    <GuideEntityEmbed Entity="GasValve" Caption=""/>
    <GuideEntityEmbed Entity="SignalControlledValve" Caption=""/>
    <GuideEntityEmbed Entity="PressureControlledValve" Caption=""/>
    <GuideEntityEmbed Entity="GasPassiveGate" Caption=""/>
    <GuideEntityEmbed Entity="GasPressureRegulator" Caption=""/>
  </Box>
  <Box>
    ## Válvulas
  </Box>
  <Box>
    [color=#999999][italic]Controlando o fluxo de gás através dos tubos[italic][/color]
  </Box>

  <Box>
    <GuideEntityEmbed Entity="GasMixer" Caption=""/>
    <GuideEntityEmbed Entity="GasFilter" Caption=""/>
  </Box>
  <Box>
    ## Mistura e Filtragem
  </Box>
  <Box>
    [color=#999999][italic]Manipulando a composição do gás[italic][/color]
  </Box>

  <Box>
    <GuideEntityEmbed Entity="AirCanister" Caption=""/>
    <GuideEntityEmbed Entity="OxygenCanister" Caption=""/>
    <GuideEntityEmbed Entity="NitrogenCanister" Caption=""/>
    <GuideEntityEmbed Entity="CarbonDioxideCanister" Caption=""/>
    <GuideEntityEmbed Entity="StorageCanister" Caption=""/>
    <GuideEntityEmbed Entity="GasPort" Caption=""/>
  </Box>
  <Box>
    ## Cilindros de Gás
  </Box>
  <Box>
    [color=#999999][italic]Armazenando e transportando gás para fácil uso pela tripulação[italic][/color]
  </Box>

  <Box>
    <GuideEntityEmbed Entity="SpaceHeater" Caption=""/>
    <GuideEntityEmbed Entity="GasThermoMachineHeater" Caption=""/>
    <GuideEntityEmbed Entity="GasThermoMachineFreezer" Caption=""/>
    <GuideEntityEmbed Entity="HeatExchanger" Caption=""/>
  </Box>
  <Box>
    ## Termomáquinas e Radiadores
  </Box>
  <Box>
    [color=#999999][italic]Manipulando a temperatura de gases em uma rede de tubos ou atmosfera[italic][/color]
  </Box>

  <Box>
    <GuideEntityEmbed Entity="BaseGasCondenser" Caption=""/>
  </Box>
  <Box>
    ## Condensação de Gás
  </Box>
  <Box>
    [color=#999999][italic]Condensando gases para uso posterior[italic][/color]
  </Box>
</Document>
